[{"date": "Sun, Sep 17, 2023", "game": {"number": "296", "type": "Regular Season", "time": "6:30 PM", "date": "Sep 17, 2023", "gameId": "1425592", "homeTeam": {"id": "140818", "name": "CT Polar Bears", "logo": "https://imagedelivery.net/ErrQpIaCOWR-Tz51PhN1zA/36bd4159-20b2-4ddf-a236-dbd587eab400/256", "division": "14U Diamond", "record": "(2 - 0 - 0)", "recap": [{"playerName": "ALEXIS SAVAGE", "time": "13:08 2nd", "id": "2041399"}, {"playerName": "EMMA GROSS", "time": "10:05 2nd", "id": "2041391"}, {"playerName": "ESTHER SCHONBERGER", "time": "11:56 3rd", "id": "2041400"}, {"playerName": "EMMA GROSS", "time": "10:43 3rd", "id": "2041391"}, {"playerName": "PEIGHTON SALERNO", "time": "09:03 3rd", "id": "2041392"}]}, "visitorTeam": {"id": "140811", "name": "NJ Bandits", "logo": "https://imagedelivery.net/ErrQpIaCOWR-Tz51PhN1zA/81232c6e-aa30-48e4-ce9c-a705e63a7400/256", "division": "14U Diamond", "record": "(1 - 3 - 0)", "recap": [{"playerName": "ALEXANDRA SKARKAS", "time": "06:00 1st", "id": "2041193"}]}, "scoresByPeriod": [{"title": "1ST", "homeGoals": "0", "visitorGoals": "1"}, {"title": "2ND", "homeGoals": "2", "visitorGoals": "0"}, {"title": "3RD", "homeGoals": "3", "visitorGoals": "0"}], "finalScore": {"homeGoals": 5, "visitorGoals": 1}}}, {"date": "Sun, Sep 17, 2023", "game": {"number": "313", "type": "Regular Season", "time": "4:45 PM", "date": "Sep 17, 2023", "gameId": "1425580", "homeTeam": {"id": "140813", "name": "Stateline Hawks", "logo": "https://imagedelivery.net/ErrQpIaCOWR-Tz51PhN1zA/ef1e7d2c-5928-419d-8ed3-257cc821ca00/256", "division": "14U Diamond", "record": "(1 - 2 - 0)", "recap": [{"playerName": "ADDISON PINNOW", "time": "07:12 2nd", "id": "2031270"}, {"playerName": "ANNA TERJANIAN", "time": "01:32 2nd", "id": "2031269"}]}, "visitorTeam": {"id": "140821", "name": "PTL Orange", "logo": "https://imagedelivery.net/ErrQpIaCOWR-Tz51PhN1zA/fe5028dd-daf7-40d7-1428-81f129714b00/256", "division": "14U Diamond", "record": "(4 - 2 - 0)", "recap": [{"playerName": "HARKIRAN SANDHU", "time": "03:40 1st", "id": "2050822"}, {"playerName": "SAMANTHA LUI", "time": "01:01 1st", "id": "2050829"}, {"playerName": "EMMA HLINKA", "time": "15:34 3rd", "id": "2050823"}]}, "scoresByPeriod": [{"title": "1ST", "homeGoals": "0", "visitorGoals": "2"}, {"title": "2ND", "homeGoals": "2", "visitorGoals": "0"}, {"title": "3RD", "homeGoals": "0", "visitorGoals": "1"}], "finalScore": {"homeGoals": 2, "visitorGoals": 3}}}, {"date": "Sun, Sep 17, 2023", "game": {"number": "529", "type": "Regular Season", "time": "3:45 PM", "date": "Sep 17, 2023", "gameId": "1425294", "homeTeam": {"id": "140825", "name": "WBS Lady Knights", "logo": "https://imagedelivery.net/ErrQpIaCOWR-Tz51PhN1zA/b70ba6b1-c5cd-46b1-2bc8-2e11661d9300/256", "division": "14U Diamond", "record": "(0 - 2 - 0)", "recap": [{"playerName": "SOFIA MAKUKOVA", "time": "15:47 2nd", "id": "2045041"}]}, "visitorTeam": {"id": "140822", "name": "STJ", "logo": "https://imagedelivery.net/ErrQpIaCOWR-Tz51PhN1zA/e3408b2f-5355-461a-c784-3e494cd66a00/256", "division": "14U Diamond", "record": "(4 - 2 - 0)", "recap": [{"playerName": "VIRGINIA PURKEY", "time": "06:06 1st", "id": "2031138"}, {"playerName": "PAYTON LOGOTHETY", "time": "05:31 1st", "id": "2031133"}, {"playerName": "LUCY JORJANI", "time": "10:58 2nd", "id": "2031135"}, {"playerName": "LUCY JORJANI", "time": "05:20 2nd", "id": "2031135"}, {"playerName": "LUCY JORJANI", "time": "01:23 2nd", "id": "2031135"}, {"playerName": "LUCILIA ALY", "time": "03:32 3rd", "id": "2031126"}]}, "scoresByPeriod": [{"title": "1ST", "homeGoals": "0", "visitorGoals": "2"}, {"title": "2ND", "homeGoals": "1", "visitorGoals": "3"}, {"title": "3RD", "homeGoals": "0", "visitorGoals": "1"}], "finalScore": {"homeGoals": 1, "visitorGoals": 6}}}, {"date": "Sun, Sep 17, 2023", "game": {"number": "312", "type": "Regular Season", "time": "11:44 AM", "date": "Sep 17, 2023", "gameId": "1425579", "homeTeam": {"id": "140813", "name": "Stateline Hawks", "logo": "https://imagedelivery.net/ErrQpIaCOWR-Tz51PhN1zA/ef1e7d2c-5928-419d-8ed3-257cc821ca00/256", "division": "14U Diamond", "record": "(1 - 2 - 0)", "recap": [{"playerName": "OLIVE LABELLE", "time": "11:28 1st", "id": "2031273"}, {"playerName": "ANNA TERJANIAN", "time": "09:46 3rd", "id": "2031269"}]}, "visitorTeam": {"id": "140821", "name": "PTL Orange", "logo": "https://imagedelivery.net/ErrQpIaCOWR-Tz51PhN1zA/fe5028dd-daf7-40d7-1428-81f129714b00/256", "division": "14U Diamond", "record": "(4 - 2 - 0)", "recap": []}, "scoresByPeriod": [{"title": "1ST", "homeGoals": "1", "visitorGoals": "0"}, {"title": "2ND", "homeGoals": "0", "visitorGoals": "0"}, {"title": "3RD", "homeGoals": "1", "visitorGoals": "0"}], "finalScore": {"homeGoals": 2, "visitorGoals": 0}}}, {"date": "Sun, Sep 17, 2023", "game": {"number": "528", "type": "Regular Season", "time": "10:15 AM", "date": "Sep 17, 2023", "gameId": "1425293", "homeTeam": {"id": "140825", "name": "WBS Lady Knights", "logo": "https://imagedelivery.net/ErrQpIaCOWR-Tz51PhN1zA/b70ba6b1-c5cd-46b1-2bc8-2e11661d9300/256", "division": "14U Diamond", "record": "(0 - 2 - 0)", "recap": [{"playerName": "ADDYSON BEST", "time": "07:39 3rd", "id": "2045044"}]}, "visitorTeam": {"id": "140822", "name": "STJ", "logo": "https://imagedelivery.net/ErrQpIaCOWR-Tz51PhN1zA/e3408b2f-5355-461a-c784-3e494cd66a00/256", "division": "14U Diamond", "record": "(4 - 2 - 0)", "recap": [{"playerName": "LUCY JORJANI", "time": "05:35 1st", "id": "2031135"}, {"playerName": "VIRGINIA PURKEY", "time": "00:49 1st", "id": "2031138"}, {"playerName": "PAYTON LOGOTHETY", "time": "13:31 3rd", "id": "2031133"}, {"playerName": "RAGAN HENRY", "time": "07:20 3rd", "id": "2031128"}, {"playerName": "PAYTON LOGOTHETY", "time": "04:58 3rd", "id": "2031133"}]}, "scoresByPeriod": [{"title": "1ST", "homeGoals": "0", "visitorGoals": "2"}, {"title": "2ND", "homeGoals": "0", "visitorGoals": "0"}, {"title": "3RD", "homeGoals": "1", "visitorGoals": "3"}], "finalScore": {"homeGoals": 1, "visitorGoals": 5}}}, {"date": "Sat, Sep 16, 2023", "game": {"number": "401", "type": "Regular Season", "time": "5:18 PM", "date": "Sep 16, 2023", "gameId": "1425487", "homeTeam": {"id": "140820", "name": "LVPY", "logo": "https://imagedelivery.net/ErrQpIaCOWR-Tz51PhN1zA/a8516f95-dba4-4762-fadc-19001c3c7600/256", "division": "14U Diamond", "record": "(0 - 2 - 0)", "recap": []}, "visitorTeam": {"id": "140822", "name": "STJ", "logo": "https://imagedelivery.net/ErrQpIaCOWR-Tz51PhN1zA/e3408b2f-5355-461a-c784-3e494cd66a00/256", "division": "14U Diamond", "record": "(4 - 2 - 0)", "recap": [{"playerName": "PAYTON LOGOTHETY", "time": "14:00 1st", "id": "2031133"}, {"playerName": "TWILA SHAPPY-BEHN", "time": "12:44 1st", "id": "2031132"}, {"playerName": "PAYTON LOGOTHETY", "time": "09:43 2nd", "id": "2031133"}, {"playerName": "LUCY JORJANI", "time": "07:24 2nd", "id": "2031135"}, {"playerName": "LUCILIA ALY", "time": "06:06 2nd", "id": "2031126"}, {"playerName": "PAYTON LOGOTHETY", "time": "05:18 2nd", "id": "2031133"}, {"playerName": "CARMEN COREAS", "time": "00:30 2nd", "id": "2031137"}, {"playerName": "VIRGINIA PURKEY", "time": "11:39 3rd", "id": "2031138"}, {"playerName": "CARMEN COREAS", "time": "07:38 3rd", "id": "2031137"}, {"playerName": "RAGAN HENRY", "time": "03:42 3rd", "id": "2031128"}, {"playerName": "PAYTON LOGOTHETY", "time": "02:45 3rd", "id": "2031133"}, {"playerName": "KEZIAH MONK", "time": "00:01 3rd", "id": "2031131"}]}, "scoresByPeriod": [{"title": "1ST", "homeGoals": "0", "visitorGoals": "2"}, {"title": "2ND", "homeGoals": "0", "visitorGoals": "5"}, {"title": "3RD", "homeGoals": "0", "visitorGoals": "5"}], "finalScore": {"homeGoals": 0, "visitorGoals": 12}}}, {"date": "Sat, Sep 16, 2023", "game": {"number": "213", "type": "Regular Season", "time": "12:49 PM", "date": "Sep 16, 2023", "gameId": "1425638", "homeTeam": {"id": "140811", "name": "NJ Bandits", "logo": "https://imagedelivery.net/ErrQpIaCOWR-Tz51PhN1zA/81232c6e-aa30-48e4-ce9c-a705e63a7400/256", "division": "14U Diamond", "record": "(1 - 3 - 0)", "recap": [{"playerName": "REMY CINQUINO", "time": "02:49 1st", "id": "2041189"}]}, "visitorTeam": {"id": "140818", "name": "CT Polar Bears", "logo": "https://imagedelivery.net/ErrQpIaCOWR-Tz51PhN1zA/36bd4159-20b2-4ddf-a236-dbd587eab400/256", "division": "14U Diamond", "record": "(2 - 0 - 0)", "recap": [{"playerName": "CHARLOTTE REIDEL", "time": "09:15 2nd", "id": "2041398"}, {"playerName": "CHARLOTTE REIDEL", "time": "03:10 3rd", "id": "2041398"}]}, "scoresByPeriod": [{"title": "1ST", "homeGoals": "1", "visitorGoals": "0"}, {"title": "2ND", "homeGoals": "0", "visitorGoals": "1"}, {"title": "3RD", "homeGoals": "0", "visitorGoals": "1"}], "finalScore": {"homeGoals": 1, "visitorGoals": 2}}}, {"date": "Sat, Sep 16, 2023", "game": {"number": "400", "type": "Regular Season", "time": "11:48 AM", "date": "Sep 16, 2023", "gameId": "1425486", "homeTeam": {"id": "140820", "name": "LVPY", "logo": "https://imagedelivery.net/ErrQpIaCOWR-Tz51PhN1zA/a8516f95-dba4-4762-fadc-19001c3c7600/256", "division": "14U Diamond", "record": "(0 - 2 - 0)", "recap": []}, "visitorTeam": {"id": "140822", "name": "STJ", "logo": "https://imagedelivery.net/ErrQpIaCOWR-Tz51PhN1zA/e3408b2f-5355-461a-c784-3e494cd66a00/256", "division": "14U Diamond", "record": "(4 - 2 - 0)", "recap": [{"playerName": "PAYTON LOGOTHETY", "time": "15:34 1st", "id": "2031133"}, {"playerName": "RAGAN HENRY", "time": "14:58 1st", "id": "2031128"}, {"playerName": "TWILA SHAPPY-BEHN", "time": "13:17 1st", "id": "2031132"}, {"playerName": "VIRGINIA PURKEY", "time": "05:20 1st", "id": "2031138"}, {"playerName": "VIRGINIA PURKEY", "time": "04:29 1st", "id": "2031138"}, {"playerName": "MADELYN SCHNUR", "time": "03:17 1st", "id": "2031134"}, {"playerName": "VICTORIA RANDALL", "time": "08:06 2nd", "id": "2031139"}, {"playerName": "RAGAN HENRY", "time": "04:46 3rd", "id": "2031128"}, {"playerName": "PAYTON LOGOTHETY", "time": "03:38 3rd", "id": "2031133"}, {"playerName": "VIRGINIA PURKEY", "time": "01:08 3rd", "id": "2031138"}]}, "scoresByPeriod": [{"title": "1ST", "homeGoals": "0", "visitorGoals": "6"}, {"title": "2ND", "homeGoals": "0", "visitorGoals": "1"}, {"title": "3RD", "homeGoals": "0", "visitorGoals": "3"}], "finalScore": {"homeGoals": 0, "visitorGoals": 10}}}, {"date": "Sun, Sep 10, 2023", "game": {"number": "212", "type": "Regular Season", "time": "5:15 PM", "date": "Sep 10, 2023", "gameId": "1425637", "homeTeam": {"id": "140811", "name": "NJ Bandits", "logo": "https://imagedelivery.net/ErrQpIaCOWR-Tz51PhN1zA/81232c6e-aa30-48e4-ce9c-a705e63a7400/256", "division": "14U Diamond", "record": "(1 - 3 - 0)", "recap": []}, "visitorTeam": {"id": "140815", "name": "PTL Black", "logo": "https://imagedelivery.net/ErrQpIaCOWR-Tz51PhN1zA/630e6f85-98c7-492b-4a0d-fb2fa99aa600/256", "division": "14U Diamond", "record": "(1 - 2 - 0)", "recap": [{"playerName": "FIONA HANNAFORD", "time": "11:24 1st", "id": "2050810"}, {"playerName": "MALAC RAMADAN", "time": "01:34 1st", "id": "2050814"}, {"playerName": "SOPHIA ALLAM", "time": "14:49 3rd", "id": "2050808"}, {"playerName": "GEORGIA FOWLER", "time": "03:41 3rd", "id": "2050812"}]}, "scoresByPeriod": [{"title": "1ST", "homeGoals": "0", "visitorGoals": "2"}, {"title": "2ND", "homeGoals": "0", "visitorGoals": "0"}, {"title": "3RD", "homeGoals": "0", "visitorGoals": "2"}], "finalScore": {"homeGoals": 0, "visitorGoals": 4}}}, {"date": "Sun, Sep 10, 2023", "game": {"number": "119", "type": "Regular Season", "time": "1:00 PM", "date": "Sep 10, 2023", "gameId": "1425731", "homeTeam": {"id": "140822", "name": "STJ", "logo": "https://imagedelivery.net/ErrQpIaCOWR-Tz51PhN1zA/e3408b2f-5355-461a-c784-3e494cd66a00/256", "division": "14U Diamond", "record": "(4 - 2 - 0)", "recap": [{"playerName": "VICTORIA RANDALL", "time": "10:17 1st", "id": "2031139"}, {"playerName": "VIRGINIA PURKEY", "time": "02:14 2nd", "id": "2031138"}]}, "visitorTeam": {"id": "140821", "name": "PTL Orange", "logo": "https://imagedelivery.net/ErrQpIaCOWR-Tz51PhN1zA/fe5028dd-daf7-40d7-1428-81f129714b00/256", "division": "14U Diamond", "record": "(4 - 2 - 0)", "recap": [{"playerName": "ALEXIS MOSLIN", "time": "03:57 2nd", "id": "2050827"}, {"playerName": "SAMANTHA LUI", "time": "01:38 2nd", "id": "2050829"}, {"playerName": "ALLISON DEFAZIO", "time": "00:01 2nd", "id": "2050832"}, {"playerName": "LAYLA SOSNER", "time": "04:04 3rd", "id": "2050828"}]}, "scoresByPeriod": [{"title": "1ST", "homeGoals": "1", "visitorGoals": "0"}, {"title": "2ND", "homeGoals": "1", "visitorGoals": "3"}, {"title": "3RD", "homeGoals": "0", "visitorGoals": "1"}], "finalScore": {"homeGoals": 2, "visitorGoals": 4}}}, {"date": "Sun, Sep 10, 2023", "game": {"number": "211", "type": "Regular Season", "time": "12:45 PM", "date": "Sep 10, 2023", "gameId": "1425636", "homeTeam": {"id": "140811", "name": "NJ Bandits", "logo": "https://imagedelivery.net/ErrQpIaCOWR-Tz51PhN1zA/81232c6e-aa30-48e4-ce9c-a705e63a7400/256", "division": "14U Diamond", "record": "(1 - 3 - 0)", "recap": [{"playerName": "REMY CINQUINO", "time": "14:11 1st", "id": "2041189"}, {"playerName": "MERYL LAWSON", "time": "13:51 2nd", "id": "2041183"}, {"playerName": "DELANEY COZINE", "time": "06:42 3rd", "id": "2041181"}]}, "visitorTeam": {"id": "140813", "name": "Stateline Hawks", "logo": "https://imagedelivery.net/ErrQpIaCOWR-Tz51PhN1zA/ef1e7d2c-5928-419d-8ed3-257cc821ca00/256", "division": "14U Diamond", "record": "(1 - 2 - 0)", "recap": [{"playerName": "SOPHIE FISHER", "time": "11:22 2nd", "id": "2031264"}, {"playerName": "SOPHIE FISHER", "time": "00:34 2nd", "id": "2031264"}]}, "scoresByPeriod": [{"title": "1ST", "homeGoals": "1", "visitorGoals": "0"}, {"title": "2ND", "homeGoals": "1", "visitorGoals": "2"}, {"title": "3RD", "homeGoals": "1", "visitorGoals": "0"}], "finalScore": {"homeGoals": 3, "visitorGoals": 2}}}, {"date": "Sun, Sep 10, 2023", "game": {"number": "118", "type": "Regular Season", "time": "8:39 AM", "date": "Sep 10, 2023", "gameId": "1425730", "homeTeam": {"id": "140822", "name": "STJ", "logo": "https://imagedelivery.net/ErrQpIaCOWR-Tz51PhN1zA/e3408b2f-5355-461a-c784-3e494cd66a00/256", "division": "14U Diamond", "record": "(4 - 2 - 0)", "recap": [{"playerName": "CARMEN COREAS", "time": "03:24 2nd", "id": "2031137"}, {"playerName": "CARMEN COREAS", "time": "08:15 3rd", "id": "2031137"}]}, "visitorTeam": {"id": "140821", "name": "PTL Orange", "logo": "https://imagedelivery.net/ErrQpIaCOWR-Tz51PhN1zA/fe5028dd-daf7-40d7-1428-81f129714b00/256", "division": "14U Diamond", "record": "(4 - 2 - 0)", "recap": [{"playerName": "ALEXIS MOSLIN", "time": "02:37 2nd", "id": "2050827"}, {"playerName": "JOSEPHINE BASORA", "time": "13:34 3rd", "id": "2050831"}, {"playerName": "SAMANTHA LUI", "time": "10:37 3rd", "id": "2050829"}, {"playerName": "ABIGAIL EHRET", "time": "00:30 3rd", "id": "2050824"}]}, "scoresByPeriod": [{"title": "1ST", "homeGoals": "0", "visitorGoals": "0"}, {"title": "2ND", "homeGoals": "1", "visitorGoals": "1"}, {"title": "3RD", "homeGoals": "1", "visitorGoals": "3"}], "finalScore": {"homeGoals": 2, "visitorGoals": 4}}}, {"date": "Sat, Sep 9, 2023", "game": {"number": "283", "type": "Regular Season", "time": "5:18 PM", "date": "Sep 9, 2023", "gameId": "1425617", "homeTeam": {"id": "140824", "name": "MYHA Gold", "logo": "https://imagedelivery.net/ErrQpIaCOWR-Tz51PhN1zA/bea3973a-2353-42af-0ff4-dbf8599bdd00/256", "division": "14U Diamond", "record": "(1 - 1 - 0)", "recap": [{"playerName": "JULIA REITZ", "time": "05:19 1st", "id": "2041461"}, {"playerName": "MOLLY KRESSE", "time": "05:41 3rd", "id": "2041458"}]}, "visitorTeam": {"id": "140821", "name": "PTL Orange", "logo": "https://imagedelivery.net/ErrQpIaCOWR-Tz51PhN1zA/fe5028dd-daf7-40d7-1428-81f129714b00/256", "division": "14U Diamond", "record": "(4 - 2 - 0)", "recap": [{"playerName": "JOSEPHINE BASORA", "time": "10:37 2nd", "id": "2050831"}]}, "scoresByPeriod": [{"title": "1ST", "homeGoals": "1", "visitorGoals": "0"}, {"title": "2ND", "homeGoals": "0", "visitorGoals": "1"}, {"title": "3RD", "homeGoals": "1", "visitorGoals": "0"}], "finalScore": {"homeGoals": 2, "visitorGoals": 1}}}, {"date": "Sat, Sep 9, 2023", "game": {"number": "446", "type": "Regular Season", "time": "5:14 PM", "date": "Sep 9, 2023", "gameId": "1425426", "homeTeam": {"id": "140815", "name": "PTL Black", "logo": "https://imagedelivery.net/ErrQpIaCOWR-Tz51PhN1zA/630e6f85-98c7-492b-4a0d-fb2fa99aa600/256", "division": "14U Diamond", "record": "(1 - 2 - 0)", "recap": []}, "visitorTeam": {"id": "140816", "name": "MYHA Blue", "logo": "https://imagedelivery.net/ErrQpIaCOWR-Tz51PhN1zA/9f9e737d-963e-41df-e47b-583e97b3d200/256", "division": "14U Diamond", "record": "(2 - 0 - 0)", "recap": [{"playerName": "HARPER LANPHER", "time": "04:44 2nd", "id": "2041444"}]}, "scoresByPeriod": [{"title": "1ST", "homeGoals": "0", "visitorGoals": "0"}, {"title": "2ND", "homeGoals": "0", "visitorGoals": "1"}, {"title": "3RD", "homeGoals": "0", "visitorGoals": "0"}], "finalScore": {"homeGoals": 0, "visitorGoals": 1}}}, {"date": "Sat, Sep 9, 2023", "game": {"number": "445", "type": "Regular Season", "time": "12:45 PM", "date": "Sep 9, 2023", "gameId": "1425425", "homeTeam": {"id": "140815", "name": "PTL Black", "logo": "https://imagedelivery.net/ErrQpIaCOWR-Tz51PhN1zA/630e6f85-98c7-492b-4a0d-fb2fa99aa600/256", "division": "14U Diamond", "record": "(1 - 2 - 0)", "recap": []}, "visitorTeam": {"id": "140816", "name": "MYHA Blue", "logo": "https://imagedelivery.net/ErrQpIaCOWR-Tz51PhN1zA/9f9e737d-963e-41df-e47b-583e97b3d200/256", "division": "14U Diamond", "record": "(2 - 0 - 0)", "recap": [{"playerName": "EVELYN MAY", "time": "02:05 2nd", "id": "2041452"}]}, "scoresByPeriod": [{"title": "1ST", "homeGoals": "0", "visitorGoals": "0"}, {"title": "2ND", "homeGoals": "0", "visitorGoals": "1"}, {"title": "3RD", "homeGoals": "0", "visitorGoals": "0"}], "finalScore": {"homeGoals": 0, "visitorGoals": 1}}}, {"date": "Sat, Sep 9, 2023", "game": {"number": "282", "type": "Regular Season", "time": "12:30 PM", "date": "Sep 9, 2023", "gameId": "1425616", "homeTeam": {"id": "140824", "name": "MYHA Gold", "logo": "https://imagedelivery.net/ErrQpIaCOWR-Tz51PhN1zA/bea3973a-2353-42af-0ff4-dbf8599bdd00/256", "division": "14U Diamond", "record": "(1 - 1 - 0)", "recap": [{"playerName": "JULIA REITZ", "time": "09:34 2nd", "id": "2041461"}, {"playerName": "GABRIELA REYES", "time": "01:54 2nd", "id": "2041457"}]}, "visitorTeam": {"id": "140821", "name": "PTL Orange", "logo": "https://imagedelivery.net/ErrQpIaCOWR-Tz51PhN1zA/fe5028dd-daf7-40d7-1428-81f129714b00/256", "division": "14U Diamond", "record": "(4 - 2 - 0)", "recap": [{"playerName": "PIA SINGH", "time": "12:28 2nd", "id": "2050834"}, {"playerName": "SAMANTHA LUI", "time": "09:24 2nd", "id": "2050829"}, {"playerName": "PIA SINGH", "time": "00:28 2nd", "id": "2050834"}, {"playerName": "PIA SINGH", "time": "02:11 3rd", "id": "2050834"}]}, "scoresByPeriod": [{"title": "1ST", "homeGoals": "0", "visitorGoals": "0"}, {"title": "2ND", "homeGoals": "2", "visitorGoals": "3"}, {"title": "3RD", "homeGoals": "0", "visitorGoals": "1"}], "finalScore": {"homeGoals": 2, "visitorGoals": 4}}}, {"date": "Sat, Sep 9, 2023", "game": {"number": "154", "type": "Regular Season", "time": "12:00 PM", "date": "Sep 9, 2023", "gameId": "1425765", "homeTeam": {"id": "140810", "name": "MassConn United Hockey Club", "logo": "https://imagedelivery.net/ErrQpIaCOWR-Tz51PhN1zA/e5619870-a06f-48d3-3269-30289c9eb000/256", "division": "14U Diamond", "record": "(1 - 0 - 0)", "recap": [{"playerName": "GRACE PACHOLSKI", "time": "06:12 2nd", "id": "2041562"}, {"playerName": "GRACE PACHOLSKI", "time": "04:30 2nd", "id": "2041562"}, {"playerName": "KAELYN DION", "time": "03:46 2nd", "id": "2041552"}, {"playerName": "KAELYN DION", "time": "00:11 2nd", "id": "2041552"}]}, "visitorTeam": {"id": "140826", "name": "CT Ice Cats", "logo": "https://imagedelivery.net/ErrQpIaCOWR-Tz51PhN1zA/e51e4f33-445f-4834-5d34-75f3d2bd8d00/256", "division": "14U Diamond", "record": "(0 - 1 - 0)", "recap": [{"playerName": "CLAIRE HICKEY", "time": "04:08 2nd", "id": "2044336"}]}, "scoresByPeriod": [{"title": "1ST", "homeGoals": "0", "visitorGoals": "0"}, {"title": "2ND", "homeGoals": "4", "visitorGoals": "1"}, {"title": "3RD", "homeGoals": "0", "visitorGoals": "0"}], "finalScore": {"homeGoals": 4, "visitorGoals": 1}}}]